algo/__init__.py
algo/abstract_summarizer_algo.py
algo/dummy_algo.py
algo/summ.py
algo/text_rank_algo.py
algo/tools/__init__.py
algo/tools/cosine_similarity.py
algo/tools/tf_idf.py
algo/tools/utils.py
text_summarizer/__init__.py
text_summarizer/text_summarizer.py
text_summarizer-0.0.4.dist-info/METADATA
text_summarizer-0.0.4.dist-info/RECORD
text_summarizer-0.0.4.dist-info/WHEEL
text_summarizer-0.0.4.dist-info/top_level.txt
