Metadata-Version: 2.1
Name: text-summarizer
Version: 0.0.4
Summary: A text summarization package
Home-page: https://github.com/franfj/Summarizer
Author: Francisco Javier Rodrigo Gines
Author-email: franjrg94@gmail.com
License: UNKNOWN
Platform: UNKNOWN
Classifier: Programming Language :: Python :: 2.7
Classifier: Development Status :: 4 - Beta  
Classifier: License :: OSI Approved :: GNU General Public License v3 (GPLv3)  
Classifier: Operating System :: OS Independent
